scalg/__init__.py
scalg/scalg.py
scalg/version.py
scalg-0.1.5.3.dist-info/LICENSE
scalg-0.1.5.3.dist-info/METADATA
scalg-0.1.5.3.dist-info/WHEEL
scalg-0.1.5.3.dist-info/top_level.txt
scalg-0.1.5.3.dist-info/RECORD
