Metadata-Version: 2.1
Name: scalg
Version: 0.1.5.3
Summary: A Python list scoring algorithm. Analyse data file using a range based procentual proximity algorithm and calculate the linear maximum likelihood.
Home-page: https://github.com/markmelnic/scalg
Author: Mark Melnic
Author-email: me@markmelnic.com
License: MIT
Classifier: Intended Audience :: Developers
Classifier: Natural Language :: English
Classifier: License :: OSI Approved :: MIT License
Classifier: Programming Language :: Python :: 3
Classifier: Programming Language :: Python :: 3.6
Classifier: Programming Language :: Python :: 3.7
Classifier: Programming Language :: Python :: 3.8
Classifier: Programming Language :: Python :: 3.9
Requires-Python: ==3.*
License-File: LICENSE
